{
  "public_id": "drv_9d25d0c9dcc1",
  "driver": "Dmitriy Sukharev",
  "summary": {
    "points": 71,
    "average_points_per_race": 14.2,
    "races": 5,
    "wins": 1,
    "podiums": 3,
    "average_finish": 5.4,
    "best_lap": "1:47.245",
    "best_lap_ms": 107245,
    "best_lap_track": "monza",
    "best_lap_car_model_id": 35,
    "best_lap_car_name_raw": "McLaren 720S GT3 Evo 2023",
    "best_lap_car_name": "McLaren 720S GT3 Evo",
    "best_lap_session_type": "Q",
    "average_pace_ms": 108587,
    "average_pace": "1:48.587",
    "penalty_count": 0,
    "penalty_points": 0,
    "fastest_lap_awards": 1,
    "most_raced_track": "monza",
    "last_race_at": "2026-03-17T23:00:10",
    "last_seen": "2026-03-17T23:11:25",
    "win_rate": 20.0,
    "podium_rate": 60.0,
    "average_positions_delta": 17.2,
    "positions_delta_races": 5
  },
  "recent_form": [
    17,
    4,
    2,
    1,
    3
  ],
  "track_stats": [
    {
      "track": "monza",
      "races": 5,
      "wins": 1,
      "podiums": 3,
      "points": 71,
      "finish_sum": 27,
      "average_finish": 5.4,
      "best_lap_ms": 107437,
      "best_lap": "1:47.437"
    }
  ],
  "race_history": [
    {
      "race_id": "260317_230010_R.json",
      "finished_at": "2026-03-17T23:00:10",
      "track": "monza",
      "car_model_id": 35,
      "car_name_raw": "McLaren 720S GT3 Evo 2023",
      "car_name": "McLaren 720S GT3 Evo",
      "position": 17,
      "participants_count": 42,
      "winner": "Oscar Cnac",
      "points": 0,
      "qualifying_position": 30,
      "start_position": 30,
      "start_position_source": "qualifying_car_id",
      "positions_delta": 13,
      "positions_gained": 13,
      "positions_lost": 0,
      "best_lap": "1:48.002",
      "best_lap_ms": 108002,
      "total_time": "11:26.726",
      "total_time_ms": 686726,
      "gap": "0:00.000",
      "gap_ms": 0,
      "lap_count": 6,
      "counted_for_stats": true,
      "had_best_lap": false,
      "penalty_count": 0,
      "penalty_points": 0
    },
    {
      "race_id": "260316_235533_R.json",
      "finished_at": "2026-03-16T23:55:33",
      "track": "monza",
      "car_model_id": 35,
      "car_name_raw": "McLaren 720S GT3 Evo 2023",
      "car_name": "McLaren 720S GT3 Evo",
      "position": 4,
      "participants_count": 39,
      "winner": "robert René",
      "points": 12,
      "qualifying_position": 26,
      "start_position": 26,
      "start_position_source": "qualifying_car_id",
      "positions_delta": 22,
      "positions_gained": 22,
      "positions_lost": 0,
      "best_lap": "1:47.930",
      "best_lap_ms": 107930,
      "total_time": "22:01.688",
      "total_time_ms": 1321688,
      "gap": "0:18.606",
      "gap_ms": 18606,
      "lap_count": 12,
      "counted_for_stats": true,
      "had_best_lap": false,
      "penalty_count": 0,
      "penalty_points": 0
    },
    {
      "race_id": "260316_231732_R.json",
      "finished_at": "2026-03-16T23:17:32",
      "track": "monza",
      "car_model_id": 35,
      "car_name_raw": "McLaren 720S GT3 Evo 2023",
      "car_name": "McLaren 720S GT3 Evo",
      "position": 2,
      "participants_count": 37,
      "winner": "Perry Dinos",
      "points": 18,
      "qualifying_position": 26,
      "start_position": 26,
      "start_position_source": "qualifying_car_id",
      "positions_delta": 24,
      "positions_gained": 24,
      "positions_lost": 0,
      "best_lap": "1:47.627",
      "best_lap_ms": 107627,
      "total_time": "21:50.038",
      "total_time_ms": 1310038,
      "gap": "0:00.614",
      "gap_ms": 614,
      "lap_count": 12,
      "counted_for_stats": true,
      "had_best_lap": false,
      "penalty_count": 0,
      "penalty_points": 0
    },
    {
      "race_id": "260315_230844_R.json",
      "finished_at": "2026-03-15T23:08:44",
      "track": "monza",
      "car_model_id": 35,
      "car_name_raw": "McLaren 720S GT3 Evo 2023",
      "car_name": "McLaren 720S GT3 Evo",
      "position": 1,
      "participants_count": 39,
      "winner": "Dmitriy Sukharev",
      "points": 25,
      "qualifying_position": 1,
      "start_position": 1,
      "start_position_source": "qualifying_car_id",
      "positions_delta": 0,
      "positions_gained": 0,
      "positions_lost": 0,
      "best_lap": "1:47.437",
      "best_lap_ms": 107437,
      "total_time": "21:36.469",
      "total_time_ms": 1296469,
      "gap": null,
      "gap_ms": null,
      "lap_count": 12,
      "counted_for_stats": true,
      "had_best_lap": false,
      "penalty_count": 0,
      "penalty_points": 0
    },
    {
      "race_id": "260315_222825_R.json",
      "finished_at": "2026-03-15T22:28:25",
      "track": "monza",
      "car_model_id": 35,
      "car_name_raw": "McLaren 720S GT3 Evo 2023",
      "car_name": "McLaren 720S GT3 Evo",
      "position": 3,
      "participants_count": 40,
      "winner": "Aleksander Kovalev",
      "points": 16,
      "qualifying_position": 30,
      "start_position": 30,
      "start_position_source": "qualifying_car_id",
      "positions_delta": 27,
      "positions_gained": 27,
      "positions_lost": 0,
      "best_lap": "1:48.122",
      "best_lap_ms": 108122,
      "total_time": "20:14.730",
      "total_time_ms": 1214730,
      "gap": "0:10.457",
      "gap_ms": 10457,
      "lap_count": 11,
      "counted_for_stats": true,
      "had_best_lap": true,
      "penalty_count": 0,
      "penalty_points": 0
    }
  ],
  "penalties": {
    "penalty_count": 0,
    "penalty_points": 0,
    "reasons": {},
    "types": {}
  }
}